.coveragerc
.editorconfig
.gitignore
.travis.yml
LICENSE
README.md
pyproject.toml
requirements.txt
requirements_dev.txt
setup.cfg
setup.py
.github/workflows/python-publish.yml
democritus_json/__init__.py
democritus_json/json_data.py
democritus_json/json_data_temp_utils.py
democritus_json.egg-info/PKG-INFO
democritus_json.egg-info/SOURCES.txt
democritus_json.egg-info/dependency_links.txt
democritus_json.egg-info/requires.txt
democritus_json.egg-info/top_level.txt
democritus_json.egg-info/zip-safe
tests/__init__.py
tests/test_json_data.py