Metadata-Version: 2.1
Name: democritus-json
Version: 2021.1.21
Summary: Democritus functions for working with JSON.
Home-page: https://github.com/democritus-project/democritus-json
Author: Floyd Hightower
Author-email: floyd.hightower27@gmail.com
License: MIT license
Keywords: democritus,utility,python,json,json-utility,json
Platform: UNKNOWN
Classifier: Development Status :: 2 - Pre-Alpha
Classifier: Intended Audience :: Developers
Classifier: License :: OSI Approved :: MIT License
Classifier: Natural Language :: English
Classifier: Programming Language :: Python :: 3
Classifier: Programming Language :: Python :: 3.4
Classifier: Programming Language :: Python :: 3.5
Classifier: Programming Language :: Python :: 3.6
Classifier: Programming Language :: Python :: 3.7
Classifier: Programming Language :: Python :: 3.8
Classifier: Programming Language :: Python :: 3.9
